{
  "hash": "4512f481",
  "browserHash": "6850b60b",
  "optimized": {
    "react": {
      "src": "../../node_modules/react/index.js",
      "file": "react.js",
      "fileHash": "b643e66f",
      "needsInterop": true
    },
    "react-dom/client": {
      "src": "../../node_modules/react-dom/client.js",
      "file": "react-dom_client.js",
      "fileHash": "877555c6",
      "needsInterop": true
    },
    "react-router-dom": {
      "src": "../../node_modules/react-router-dom/dist/index.js",
      "file": "react-router-dom.js",
      "fileHash": "d18b9285",
      "needsInterop": false
    },
    "classnames": {
      "src": "../../node_modules/classnames/index.js",
      "file": "classnames.js",
      "fileHash": "bb5fbd85",
      "needsInterop": true
    }
  },
  "chunks": {
    "chunk-ZAUFE7H7": {
      "file": "chunk-ZAUFE7H7.js"
    },
    "chunk-UXIASGQL": {
      "file": "chunk-UXIASGQL.js"
    }
  }
}